Metadata-Version: 2.1
Name: lyynotice
Version: 1.1
Summary: lyydatapolars
Author: lyy
Author-email: 
License: MIT
License-File: LICENSE
